LICENSE
MANIFEST.in
README.rst
requirements.txt
run-unittests.sh
setup.py
test-requirements.txt
tox.ini
client/mbs-cli
conf/client_secrets.json
conf/koji.conf
conf/mock.cfg
conf/yum.conf
docs/CHANGELOG.rst
docs/CONTRIBUTING.rst
docs/DEPENDENCY_RESOLUTION.rst
docs/GATING.rst
docs/HOW_MBS_BUILDS_MODULES.rst
docs/KOJI_RESOLVER.rst
docs/MODULE_NAMING.rst
docs/OFFLINE_LOCAL_BUILDS.rst
docs/REBUILD_STRATEGIES.rst
docs/STATIC_CONTEXTS.rst
docs/VIRTUAL_MODULES.rst
fedmsg.d/mbs-logging.py
fedmsg.d/mbs-scheduler.py
fedmsg.d/module_build_service.py
module_build_service/__init__.py
module_build_service/log_workaround.py
module_build_service/manage.py
module_build_service.egg-info/PKG-INFO
module_build_service.egg-info/SOURCES.txt
module_build_service.egg-info/dependency_links.txt
module_build_service.egg-info/entry_points.txt
module_build_service.egg-info/not-zip-safe
module_build_service.egg-info/requires.txt
module_build_service.egg-info/top_level.txt
module_build_service/builder/KojiContentGenerator.py
module_build_service/builder/KojiModuleBuilder.py
module_build_service/builder/MockModuleBuilder.py
module_build_service/builder/__init__.py
module_build_service/builder/base.py
module_build_service/builder/utils.py
module_build_service/common/__init__.py
module_build_service/common/config.py
module_build_service/common/errors.py
module_build_service/common/koji.py
module_build_service/common/logger.py
module_build_service/common/messaging.py
module_build_service/common/models.py
module_build_service/common/modulemd.py
module_build_service/common/monitor.py
module_build_service/common/request_utils.py
module_build_service/common/resolve.py
module_build_service/common/retry.py
module_build_service/common/scm.py
module_build_service/common/submit.py
module_build_service/common/utils.py
module_build_service/migrations/README
module_build_service/migrations/alembic.ini
module_build_service/migrations/script.py.mako
module_build_service/resolver/DBResolver.py
module_build_service/resolver/KojiResolver.py
module_build_service/resolver/LocalResolver.py
module_build_service/resolver/MBSResolver.py
module_build_service/resolver/__init__.py
module_build_service/resolver/base.py
module_build_service/scheduler/__init__.py
module_build_service/scheduler/batches.py
