Metadata-Version: 2.1
Name: module-build-service
Version: 3.9.0
Summary: The Module Build Service for Modularity
Home-page: https://pagure.io/fm-orchestrator/
Author: The Factory 2.0 Team
Author-email: module-build-service-owner@fedoraproject.org
License: MIT
Keywords: module build service fedora modularity koji mock rpm
Classifier: Programming Language :: Python
Classifier: Topic :: Software Development :: Build Tools
License-File: LICENSE
